CONTRIBUTING.md
MANIFEST.in
README.md
change_log.md
setup.py
doc/BotNotifier.md
doc/CheckResponseCode.png
doc/DeprecatedCommands.md
doc/EepromAccess.md
doc/GCodeChanges.md
doc/GCodeProtocol.md
doc/GcodeProcessor.md
doc/GcodeStateMachine.png
doc/HostCommandSuccess.png
doc/HostToolCommandSuccess.png
doc/MCodeStateMachine.png
doc/MachineProfileSpecification.md
doc/PacketStreamDecoder.png
doc/README.md
doc/SendCommand.png
doc/SystemArchitecture.png
doc/ToolCommandSuccess.png
doc/firmwareUpdates.md
doc/s3gErrors.png
doc/s3gProtocol.md
makerbot_driver/Factory.py
makerbot_driver/GcodeAssembler.py
makerbot_driver/MachineDetector.py
makerbot_driver/MachineFactory.py
makerbot_driver/__init__.py
makerbot_driver/_version.py
makerbot_driver/constants.py
makerbot_driver/errors.py
makerbot_driver/profile.py
makerbot_driver/s3g.py
makerbot_driver.egg-info/PKG-INFO
makerbot_driver.egg-info/SOURCES.txt
makerbot_driver.egg-info/dependency_links.txt
makerbot_driver.egg-info/requires.txt
makerbot_driver.egg-info/top_level.txt
makerbot_driver/EEPROM/EepromAnalyzer.py
makerbot_driver/EEPROM/EepromReader.py
makerbot_driver/EEPROM/EepromRepairer.py
makerbot_driver/EEPROM/EepromUtilities.py
makerbot_driver/EEPROM/EepromVerifier.py
makerbot_driver/EEPROM/EepromWriter.py
makerbot_driver/EEPROM/__init__.py
makerbot_driver/EEPROM/constants.py
makerbot_driver/EEPROM/eeprom_map_4.1_0x00.json
makerbot_driver/EEPROM/eeprom_map_5.1_0x00.json
makerbot_driver/EEPROM/eeprom_map_5.2_0x00.json
makerbot_driver/EEPROM/eeprom_map_5.5_0x00.json
makerbot_driver/EEPROM/eeprom_map_6.0_0x00.json
makerbot_driver/EEPROM/eeprom_map_6.1_0x00.json
makerbot_driver/EEPROM/eeprom_map_6.2_0x00.json
makerbot_driver/EEPROM/eeprom_map_7.0_0x01.json
makerbot_driver/EEPROM/eeprom_map_7.1_0x01.json
makerbot_driver/EEPROM/eeprom_map_7.2_0x01.json
makerbot_driver/EEPROM/errors.py
makerbot_driver/Encoder/Coding.py
makerbot_driver/Encoder/Crc.py
makerbot_driver/Encoder/Packet.py
makerbot_driver/Encoder/__init__.py
makerbot_driver/FileReader/FileReader.py
makerbot_driver/FileReader/__init__.py
makerbot_driver/FileReader/constants.py
makerbot_driver/FileReader/errors.py
makerbot_driver/Firmware/Uploader.py
