Metadata-Version: 1.0
Name: makerbot-driver
Version: 0.1.3
Summary: Python driver to connect to MakerBot 3D Printers which use the s3g protocol
Home-page: http://github.com/makerbot/s3g
Author: ['Matt Mets', 'David Sayles (MBI)', 'Far McKon (MBI)']
Author-email: ['cibomahto@gmail.com', 'david.sayles@makerbot.com', 'far@makerbot.com']
License: GNU AFFERO GENERAL PUBLIC LICENSE
Platform: any
